[
    {
        "title": "Paquete pequeño",
        "image": "https://soychef.today/__export/1608085128871/sites/soychef/img/2020/12/15/multimedia_x56x.jpg_554688468.jpg",
        "summary": "Una selección de nuestros clásicos más populares.",
        "bulletPoints": [
            {
                "point": "Empanada de carne"
            },
            {
                "point": "Empanada de pollo"
            },
            {
                "point": "Salsa roja"
            },
            {
                "point": "Salsa verde"
            },
            {
                "point": "Coca-Cola"
            }
        ],
        "description": "Descubre la excelencia de nuestra marca con nuestros productos más populares. Sumérgete en una experiencia culinaria única con nuestras deliciosas empanadas y salsas que todos aman. ¡Una pequeña muestra de lo que tenemos para ofrecer!"
    },
    {
        "title": "Paquete mediano",
        "image": "https://placehold.co/74x74",
        "summary": "https://2.bp.blogspot.com/-HKRp8guNfsQ/UstlwSVfU7I/AAAAAAAADNs/EjZEzaBqAI4/s1600/CASA_VIEJA_Empanadas.jpg",
        "bulletPoints": [
            {
                "point": "Todo lo incluido en el Paquete pequeño"
            },
            {
                "point": "Empanada de queso"
            },
            {
                "point": "Limonada"
            },
            {
                "point": "Salsa de aguacate"
            },
            {
                "point": "Pepsi"
            }
        ],
        "description": "Si ya te enamoraste de nuestros clásicos y estás listo para una segunda ronda, ¡prueba el Paquete Dos! Además de nuestros favoritos, hemos incluido nuestras recomendaciones especiales para una experiencia aún más satisfactoria."
    },
    {
        "title": "Paquete grande",
        "image": "https://th.bing.com/th/id/R.a88cd7cdef657ca82c53c55b4f5d8829?rik=VetAmAQSqtsyRg&riu=http%3a%2f%2fempanadasenmedellin.com%2fwp-content%2fuploads%2f2020%2f05%2fEmpanadas-de-Iglesia.jpg&ehk=6AjUeZ1tBTClOJccnjL%2bBXziz04br%2fdzXMmUjOS17C8%3d&risl=&pid=ImgRaw&r=0",
        "summary": "La experiencia completa de nuestro variado menú en un solo paquete.",
        "bulletPoints": [
            {
                "point": "Todo lo incluido en el Paquete mediano"
            },
            {
                "point": "Empanada hawaiiana"
            },
            {
                "point": "Empanada de champiñones"
            },
            {
                "point": "Empanada de piña"
            },
            {
                "point": "Empanada de cajeta"
            },
            {
                "point": "Empanada de mole"
            },
            {
                "point": "Tamarindo"
            },
            {
                "point": "Naranjada"
            },
            {
                "point": "Piña Colada"
            },
            {
                "point": "Salsa de chile habanero"
            },
            {
                "point": "Salsa de cacahuate"
            },
            {
                "point": "Jarritos"
            },
            {
                "point": "Horchata"
            }
        ],
        "description": "Diseñado para los verdaderos amantes de las empanadas, nuestro Paquete Grande es un festín que abarca todo nuestro variado menú. Cada artículo que ofrecemos, desde las empanadas más suculentas hasta las bebidas más refrescantes y salsas irresistibles, se encuentra en este paquete. ¡Satisfacción garantizada para tu apetito aventurero!"
    }
]
